doremi/__init__.py
doremi/doremi.py
doremi/td_psola.py
doremi/tuners.py
doremi/util.py
doremi-1.0.1.dist-info/LICENSE.txt
doremi-1.0.1.dist-info/METADATA
doremi-1.0.1.dist-info/WHEEL
doremi-1.0.1.dist-info/top_level.txt
doremi-1.0.1.dist-info/RECORD
